[
  {
    "lat": 40.7127281,
    "lon": -74.0060152,
    "title": "NYPD Sees Largest Class in a Decade, with One in Four Recruits Born Abroad",
    "link": "https://lavocedinewyork.com/en/new-york/2025/08/09/nypd-sees-largest-class-in-a-decade-with-one-in-four-recruits-born-abroad/",
    "source": "La Voce di New York",
    "timestamp": "2025-08-09 13:40:35",
    "icon_url": "https://raw.githubusercontent.com/microsoft/fluentui-emoji/main/assets/Newspaper/3D/newspaper_3d.png",
    "description": "Commissioner Tisch says interest in joining the force is rebounding after years of decline"
  }
]